{
  "batchcomplete": "",
  "query": {
    "normalized": [{ "from": "Main_Page", "to": "Main Page" }],
    "pages": {
      "15580374": {
        "pageid": 15580374,
        "ns": 0,
        "title": "Main Page",
        "links": [
          { "ns": 0, "title": "10 October 2022 missile strikes on Ukraine" },
          { "ns": 0, "title": "1142" },
          { "ns": 0, "title": "1311" },
          { "ns": 0, "title": "1797" },
          { "ns": 0, "title": "1942" },
          { "ns": 0, "title": "1968" },
          { "ns": 0, "title": "2022 Crimean Bridge explosion" },
          { "ns": 0, "title": "2022 Nong Bua Lamphu attack" },
          { "ns": 0, "title": "2022 Russian invasion of Ukraine" },
          { "ns": 0, "title": "Adult Contemporary (chart)" },
          { "ns": 0, "title": "Adult Top 40" },
          { "ns": 0, "title": "Airplay" },
          { "ns": 0, "title": "Alain Aspect" },
          { "ns": 0, "title": "Alexander Hamilton U.S. Custom House" },
          { "ns": 0, "title": "Amitabh Bachchan" },
          { "ns": 0, "title": "Andr\u00e9 Chagnon" },
          { "ns": 0, "title": "Anglicanism" },
          { "ns": 0, "title": "Annie Ernaux" },
          { "ns": 0, "title": "Anthony M. DeLuca" },
          { "ns": 0, "title": "Anton Zeilinger" },
          { "ns": 0, "title": "Apollo 7" },
          { "ns": 0, "title": "Apollo program" },
          { "ns": 0, "title": "Arctic Cordillera" },
          { "ns": 0, "title": "Arthropod" },
          { "ns": 0, "title": "Battle of Camperdown" },
          { "ns": 0, "title": "Battle of Cape Esperance" },
          { "ns": 0, "title": "Billboard (magazine)" },
          { "ns": 0, "title": "Billboard Hot 100" },
          { "ns": 0, "title": "Bird migration" },
          { "ns": 0, "title": "Boat Harbour, New South Wales" },
          { "ns": 0, "title": "Calendar of saints (Church of England)" },
          { "ns": 0, "title": "Calidris" },
          { "ns": 0, "title": "Cape Canaveral" },
          { "ns": 0, "title": "Cape Canaveral Launch Complex 34" },
          { "ns": 0, "title": "Colonial Office" },
          { "ns": 0, "title": "Crimean Bridge" },
          { "ns": 0, "title": "Daglish railway station" },
          { "ns": 0, "title": "Deaths in 2022" },
          { "ns": 0, "title": "Delicate (Taylor Swift song)" },
          { "ns": 0, "title": "Doctor Who" },
          { "ns": 0, "title": "Doctor Who (season 2)" },
          { "ns": 0, "title": "East Africa Protectorate" },
          { "ns": 0, "title": "East African Mounted Rifles" },
          { "ns": 0, "title": "Edward II of England" },
          { "ns": 0, "title": "Electropop" },
          { "ns": 0, "title": "Encyclopedia" },
          { "ns": 0, "title": "English language" },
          { "ns": 0, "title": "Faustino L\u00f3pez Vargas" },
          { "ns": 0, "title": "First National Bank Tower" },
          { "ns": 0, "title": "Florida" },
          { "ns": 0, "title": "Fort Vancouver Centennial half dollar" },
          { "ns": 0, "title": "Free content" },
          { "ns": 0, "title": "French Revolutionary Wars" },
          { "ns": 0, "title": "Great knot" },
          { "ns": 0, "title": "Guadalcanal" },
          { "ns": 0, "title": "Henderson Field (Guadalcanal)" },
          { "ns": 0, "title": "House music" },
          { "ns": 0, "title": "Human spaceflight" },
          { "ns": 0, "title": "Imperial Japanese Navy" },
          { "ns": 0, "title": "James the Deacon" },
          { "ns": 0, "title": "Jin\u2013Song Wars" },
          { "ns": 0, "title": "John Clauser" },
          { "ns": 0, "title": "Kebab pizza" },
          { "ns": 0, "title": "Kingdom of England" },
          { "ns": 0, "title": "Kiriko (Overwatch)" },
          { "ns": 0, "title": "Larva" },
          { "ns": 0, "title": "List of Nobel laureates in Physics" },
          { "ns": 0, "title": "List of days of the year" },
          { "ns": 0, "title": "Loretta Lynn" },
          { "ns": 0, "title": "M Club banner" },
          { "ns": 0, "title": "Mahsa Amini protests" },
          { "ns": 0, "title": "Mainstream Top 40" },
          { "ns": 0, "title": "Mar\u00eda Teresa Ferrari" },
          { "ns": 0, "title": "Mawlid" },
          { "ns": 0, "title": "Max Martin" },
          { "ns": 0, "title": "Mulayam Singh Yadav" },
          { "ns": 0, "title": "Music video" },
          { "ns": 0, "title": "NASA" },
          { "ns": 0, "title": "National Coming Out Day" },
          { "ns": 0, "title": "Nebraska" },
          { "ns": 0, "title": "Nobel Prize in Literature" },
          { "ns": 0, "title": "Nong Bua Lamphu province" },
          { "ns": 0, "title": "October 10" },
          { "ns": 0, "title": "October 11" },
          { "ns": 0, "title": "October 12" },
          { "ns": 0, "title": "Ordinances of 1311" },
          { "ns": 0, "title": "Overwatch 2" },
          { "ns": 0, "title": "Peerage of England" },
          { "ns": 0, "title": "Peter Tobin" },
          { "ns": 0, "title": "Quantum mechanics" },
          { "ns": 0, "title": "Red knot" },
          { "ns": 0, "title": "Reputation (album)" },
          { "ns": 0, "title": "Reputation Stadium Tour" },
          { "ns": 0, "title": "Roger Robinson (academic)" },
          { "ns": 0, "title": "Rolling Stone" },
          { "ns": 0, "title": "Royal Navy" },
          { "ns": 0, "title": "Royal Netherlands Navy" },
          { "ns": 0, "title": "Sandpiper" },
          { "ns": 0, "title": "Sentimental ballad" },
          { "ns": 0, "title": "Shellback (record producer)" },
          { "ns": 0, "title": "Single (music)" },
          { "ns": 0, "title": "Slant Magazine" },
          { "ns": 0, "title": "Sleeper hit" },
          { "ns": 0, "title": "Subspecies" },
          { "ns": 0, "title": "Synthesizer" },
          { "ns": 0, "title": "Taylor Swift" },
          { "ns": 0, "title": "The Ten Year War" },
          { "ns": 0, "title": "Th\u00edch Nh\u1ea5t H\u1ea1nh" },
          { "ns": 0, "title": "Treaty of Shaoxing" },
          { "ns": 0, "title": "Tundra" },
          { "ns": 0, "title": "United States Navy" },
          { "ns": 0, "title": "Vocoder" },
          { "ns": 0, "title": "Wader" },
          { "ns": 0, "title": "Watts and Betchart murder case" },
          { "ns": 0, "title": "Wikimedia Foundation" },
          { "ns": 0, "title": "Wikipedia" },
          { "ns": 0, "title": "William Hartnell" },
          { "ns": 0, "title": "World War II" },
          { "ns": 2, "title": "User:JJ Harrison" },
          { "ns": 4, "title": "Wikipedia:About Today's featured article" },
          { "ns": 4, "title": "Wikipedia:Community portal" },
          { "ns": 4, "title": "Wikipedia:Contents/Portals" },
          { "ns": 4, "title": "Wikipedia:Featured articles" },
          { "ns": 4, "title": "Wikipedia:Featured pictures" },
          { "ns": 4, "title": "Wikipedia:Help desk" },
          { "ns": 4, "title": "Wikipedia:In the news/Candidates" },
          { "ns": 4, "title": "Wikipedia:News" },
          { "ns": 4, "title": "Wikipedia:Picture of the day/Archive" },
          { "ns": 4, "title": "Wikipedia:Recent additions" },
          { "ns": 4, "title": "Wikipedia:Reference desk" },
          { "ns": 4, "title": "Wikipedia:Selected anniversaries/October" },
          { "ns": 4, "title": "Wikipedia:Teahouse" },
          {
            "ns": 4,
            "title": "Wikipedia:Today's featured article/October 2022"
          },
          { "ns": 4, "title": "Wikipedia:Village pump" },
          { "ns": 10, "title": "Template:POTD/2022-10-08" },
          { "ns": 10, "title": "Template:POTD/2022-10-09" },
          { "ns": 10, "title": "Template:POTD/2022-10-10" },
          { "ns": 10, "title": "Template:POTD protected/2022-10-11" },
          { "ns": 10, "title": "Template:POTD protected/2022-10-12" },
          { "ns": 11, "title": "Template talk:Did you know" },
          { "ns": 12, "title": "Help:Introduction to Wikipedia" },
          { "ns": 12, "title": "Help:Your first article" },
          { "ns": 100, "title": "Portal:Current events" }
        ]
      }
    }
  },
  "limits": { "links": 500 }
}
